MANIFEST.in
requirements.txt
setup.cfg
setup.py
basis/6-31++G
basis/6-31+G
basis/6-31+G**
basis/6-311++G
basis/6-311++G(2D,2P)
basis/6-311++G**
basis/6-311+G
basis/6-311+G(2D,P)
basis/6-311G
basis/6-311G(2DF,2PD)
basis/6-31G
basis/6-31G(2DF,P)
basis/AUG-CC-PCVDZ
basis/AUG-CC-PCVQZ
basis/AUG-CC-PCVTZ
basis/AUG-CC-PVDZ
basis/AUG-CC-PVTZ
basis/CC-PCVDZ
basis/CC-PVDZ
basis/CC-PVDZ-RI
basis/CC-PVTZ
basis/CC-PVTZ-RI
basis/D-AUG-CC-PVDZ
basis/D-AUG-CC-PVQZ
basis/D-AUG-CC-PVTZ
basis/DEF2-QZVP
basis/DEF2-QZVPD
basis/DEF2-QZVPP
basis/DEF2-QZVPPD
basis/DEF2-RI-J
basis/DEF2-SV(P)
basis/DEF2-SVP
basis/DEF2-SVPD
basis/DEF2-TZVP
basis/DEF2-TZVPP
basis/DEF2-TZVPPD
basis/MIN-CC-PVDZ
basis/SADLEJ-PVTZ
basis/STO-3G
basis/STO-6G
basis/guess/DEF2-SVP-DENSITY
config/Setup.template
config/generate_setup.py
src/Makefile
src/vlx
src/dft/AOKohnShamMatrix.cpp
src/dft/AOKohnShamMatrix.hpp
src/dft/DensityGrid.cpp
src/dft/DensityGrid.hpp
src/dft/DensityGridDriver.cpp
src/dft/DensityGridDriver.hpp
src/dft/DensityGridType.hpp
src/dft/GridDriver.cpp
src/dft/GridDriver.hpp
src/dft/GtoFunc.cpp
src/dft/GtoFunc.hpp
src/dft/GtoFuncForGGA.cpp
src/dft/GtoFuncForGGA.hpp
src/dft/GtoFuncForLDA.cpp
src/dft/GtoFuncForLDA.hpp
src/dft/LebedevLaikovQuadrature.cpp
src/dft/LebedevLaikovQuadrature.hpp
src/dft/Log3Quadrature.cpp
src/dft/Log3Quadrature.hpp
src/dft/Makefile
src/dft/MolecularGrid.cpp
src/dft/MolecularGrid.hpp
src/dft/PartitionFunc.cpp
src/dft/PartitionFunc.hpp
src/dft/PrimitiveFunctional.cpp
src/dft/PrimitiveFunctional.hpp
src/dft/XCFuncType.hpp
src/dft/XCFunctional.cpp
src/dft/XCFunctional.hpp
src/dft/XCGradientGrid.cpp
src/dft/XCGradientGrid.hpp
src/dft/XCHessianGrid.cpp
src/dft/XCHessianGrid.hpp
src/dft/XCIntegrator.cpp
src/dft/XCIntegrator.hpp
src/dft/XCVarsType.hpp
src/dftfuncs/Becke88Functional.cpp
src/dftfuncs/Becke88Functional.hpp
src/dftfuncs/FunctionalParser.cpp
src/dftfuncs/FunctionalParser.hpp
src/dftfuncs/LYPFunctional.cpp
src/dftfuncs/LYPFunctional.hpp
src/dftfuncs/Makefile
veloxchem.egg-info/PKG-INFO
veloxchem.egg-info/SOURCES.txt
veloxchem.egg-info/dependency_links.txt
veloxchem.egg-info/requires.txt
veloxchem.egg-info/top_level.txt